.VERSION
AUTHORS.rst
CONTRIBUTING.rst
HISTORY.rst
LICENSE
MANIFEST.in
Pipfile
Pipfile.lock
README.rst
USAGE.rst
dev-requirements.txt
requirements.txt
setup.cfg
setup.py
docs/Makefile
docs/authors.rst
docs/conf.py
docs/contributing.rst
docs/history.rst
docs/index.rst
docs/installation.rst
docs/readme.rst
docs/usage.rst
tests/test_wikiseriesmarklib.py
wikiseriesmarklib/.VERSION
wikiseriesmarklib/AUTHORS.rst
wikiseriesmarklib/CONTRIBUTING.rst
wikiseriesmarklib/HISTORY.rst
wikiseriesmarklib/LICENSE
wikiseriesmarklib/Pipfile
wikiseriesmarklib/Pipfile.lock
wikiseriesmarklib/README.rst
wikiseriesmarklib/USAGE.rst
wikiseriesmarklib/__init__.py
wikiseriesmarklib/_version.py
wikiseriesmarklib/dev-requirements.txt
wikiseriesmarklib/requirements.txt
wikiseriesmarklib/wikiseriesmarklib.py
wikiseriesmarklib/wikiseriesmarklibexceptions.py
wikiseriesmarklib.egg-info/PKG-INFO
wikiseriesmarklib.egg-info/SOURCES.txt
wikiseriesmarklib.egg-info/dependency_links.txt
wikiseriesmarklib.egg-info/not-zip-safe
wikiseriesmarklib.egg-info/requires.txt
wikiseriesmarklib.egg-info/top_level.txt