Metadata-Version: 2.1
Name: wikiseriesmarklib
Version: 0.1.2
Summary: A library interfacing with wikipedia to retreive tv series information
Home-page: https://github.com/mmdwmeewis/wikiseriesmarklib
Author: UnknownUser
Author-email: unknownuser@unknowndomain.com
License: MIT
Keywords: wikiseriesmarklib wiki series
Classifier: Development Status :: 3 - Alpha
Classifier: Intended Audience :: Developers
Classifier: License :: OSI Approved :: MIT License
Classifier: Natural Language :: English
Classifier: Programming Language :: Python :: 3.9
License-File: LICENSE
License-File: AUTHORS.rst
